genespeak/__init__.py
genespeak/converters.py
genespeak/core.py
genespeak/dna_encoders.py
genespeak/text_strategies.py
genespeak/utils.py
genespeak-0.0.9.dist-info/LICENSE
genespeak-0.0.9.dist-info/METADATA
genespeak-0.0.9.dist-info/WHEEL
genespeak-0.0.9.dist-info/top_level.txt
genespeak-0.0.9.dist-info/RECORD
