Metadata-Version: 2.1
Name: genespeak
Version: 0.0.9
Summary: A library to encode text as DNA and decode DNA to text.
Home-page: https://github.com/sugatoray/genespeak/
Author: Sugato Ray
Author-email: sugatoray.dev@gmail.com
License: UNKNOWN
Project-URL: Documentation, https://sugatoray.github.io/genespeak/
Project-URL: Source Code, https://github.com/sugatoray/genespeak/
Project-URL: Issue Tracker, https://github.com/sugatoray/genespeak/issues
Keywords: genespeak encoding decoding text-to-dna dna-to-text
Platform: UNKNOWN
Classifier: Intended Audience :: Science/Research
Classifier: Operating System :: OS Independent
Classifier: Programming Language :: Python :: 3
Classifier: Programming Language :: Python :: 3.7
Classifier: Programming Language :: Python :: 3.8
Classifier: Programming Language :: Python :: 3.9
Classifier: License :: OSI Approved :: MIT License
Classifier: Topic :: Scientific/Engineering
Requires-Python: >=3.6
License-File: LICENSE
Provides-Extra: dev
Requires-Dist: mkdocs (>=1.2.3) ; extra == 'dev'
Requires-Dist: mkdocs-material (==8.1.3) ; extra == 'dev'
Requires-Dist: mkdocstrings (>=0.17.0) ; extra == 'dev'
Requires-Dist: mktestdocs (==0.1.2) ; extra == 'dev'
Requires-Dist: pygments (>=2.10) ; extra == 'dev'
Requires-Dist: pymdown-extensions (>=9.0) ; extra == 'dev'
Requires-Dist: interrogate (>=1.5.0) ; extra == 'dev'
Requires-Dist: flake8 (>=4.0.1) ; extra == 'dev'
Requires-Dist: pytest (>=6.2.5) ; extra == 'dev'
Requires-Dist: black (>=21.12b0) ; extra == 'dev'
Requires-Dist: pre-commit (>=2.16.0) ; extra == 'dev'
Requires-Dist: pre-commit-hooks (>=4.0.0flake8-print>=4.0.0) ; extra == 'dev'
Requires-Dist: flake8-black (>=0.2.3) ; extra == 'dev'
Requires-Dist: twine ; extra == 'dev'
Requires-Dist: setuptools ; extra == 'dev'
Requires-Dist: build ; extra == 'dev'
Requires-Dist: pkginfo (>=1.8.2) ; extra == 'dev'
